postgresdb3/__init__.py
postgresdb3/async_db.py
postgresdb3/sync_db.py
postgresdb3-0.3.3.dist-info/METADATA
postgresdb3-0.3.3.dist-info/WHEEL
postgresdb3-0.3.3.dist-info/top_level.txt
postgresdb3-0.3.3.dist-info/RECORD
