Metadata-Version: 2.4
Name: postgresdb3
Version: 0.3.3
Summary: Python uchun oddiy PostgreSQL wrapper
Author: Abdulbosit Alijonov
Project-URL: Source Code, https://github.com/AlijonovUz/PostgresDB
Classifier: Programming Language :: Python :: 3
Classifier: License :: OSI Approved :: MIT License
Classifier: Operating System :: OS Independent
Requires-Python: >=3.7
Requires-Dist: psycopg2>=2.9
Requires-Dist: asyncpg>=0.31.0
Dynamic: author
Dynamic: classifier
Dynamic: description
Dynamic: description-content-type
Dynamic: project-url
Dynamic: requires-dist
Dynamic: requires-python
Dynamic: summary
